dataknobs/__init__.py
dataknobs/flask_api.py
dataknobs/structures/__init__.py
dataknobs/utils/__init__.py
dataknobs/xization/__init__.py
dataknobs-0.1.1.dist-info/METADATA
dataknobs-0.1.1.dist-info/WHEEL
dataknobs-0.1.1.dist-info/RECORD
