Metadata-Version: 2.4
Name: dataknobs
Version: 0.1.1
Summary: Useful implementations of data structures and design patterns for AI knowledge bases. (Legacy package - please use modular packages instead)
Author-email: Spence Koehler <KoehlerSB747@gmail.com>
Requires-Python: >=3.10
Requires-Dist: dataknobs-common==1.0.0
Requires-Dist: dataknobs-structures==1.0.0
Requires-Dist: dataknobs-utils==1.0.0
Requires-Dist: dataknobs-xization==1.0.0
Requires-Dist: flask>=3.0.0
